BayesPowerlaw/__init__.py
BayesPowerlaw/docs/BayesPowerlaw.py
BayesPowerlaw/docs/Makefile
BayesPowerlaw/docs/conf.py
BayesPowerlaw/docs/documentation.rst
BayesPowerlaw/docs/index.rst
BayesPowerlaw/docs/make.bat
BayesPowerlaw/docs/mixed_powerlaw.png
BayesPowerlaw/docs/posterior_mixed_exp.png
BayesPowerlaw/docs/posterior_mixed_weight.png
BayesPowerlaw/docs/sim_fit.png
BayesPowerlaw/docs/sim_posterior.png
BayesPowerlaw/docs/sim_powerlaw.png
BayesPowerlaw/docs/tutorial.rst
BayesPowerlaw/docs/tweet_posterior.png
BayesPowerlaw/docs/tweet_powerlaw.png
BayesPowerlaw/docs/.vscode/settings.json
BayesPowerlaw-1.1.3.dist-info/LICENSE
BayesPowerlaw-1.1.3.dist-info/METADATA
BayesPowerlaw-1.1.3.dist-info/WHEEL
BayesPowerlaw-1.1.3.dist-info/top_level.txt
BayesPowerlaw-1.1.3.dist-info/RECORD
