Metadata-Version: 2.1
Name: BayesPowerlaw
Version: 1.1.3
Summary: Fitting power law distributions using Bayesian Inference
Home-page: https://github.com/AtwalLab/BayesPowerlaw
Author: Kristina Grigaityte, Gurinder Atwal
Author-email: atwal@cshl.edu
License: MIT
Keywords: power law,bayesian inference
Platform: UNKNOWN
Classifier: Development Status :: 4 - Beta
Classifier: License :: OSI Approved :: MIT License
Classifier: Programming Language :: Python :: 3.7
Classifier: Topic :: Scientific/Engineering :: Mathematics
Requires-Dist: scipy
Requires-Dist: numpy
Requires-Dist: matplotlib
